LICENSE.txt
MANIFEST.in
README.rst
setup.py
django_googledrive_storage.egg-info/PKG-INFO
django_googledrive_storage.egg-info/SOURCES.txt
django_googledrive_storage.egg-info/dependency_links.txt
django_googledrive_storage.egg-info/requires.txt
django_googledrive_storage.egg-info/top_level.txt
gdstorage/__init__.py
gdstorage/apps.py
gdstorage/storage.py