Metadata-Version: 1.1
Name: django-googledrive-storage
Version: 1.6.0
Summary: Storage implementation for Django that interacts with Google Drive
Home-page: https://github.com/torre76/django-googledrive-storage
Author: Gian Luca Dalla Torre
Author-email: gianluca.dallatorre@gmail.com
License: LICENSE.txt
Download-URL: https://github.com/torre76/django-googledrive-storage/tarball/1.6.0
Keywords: django google drive storage googledrive
Platform: UNKNOWN
Classifier: Development Status :: 5 - Production/Stable
Classifier: Framework :: Django
Classifier: License :: OSI Approved :: BSD License
Classifier: Programming Language :: Python :: 3.6
Classifier: Programming Language :: Python :: 3.7
Classifier: Programming Language :: Python :: 3.8
Classifier: Programming Language :: Python :: 3.9
Classifier: Programming Language :: Python :: 3.10
